sentry_telegram/__init__.py
sentry_telegram/plugin.py
sentry_telegram-0.6.0.dist-info/LICENSE
sentry_telegram-0.6.0.dist-info/METADATA
sentry_telegram-0.6.0.dist-info/WHEEL
sentry_telegram-0.6.0.dist-info/entry_points.txt
sentry_telegram-0.6.0.dist-info/top_level.txt
sentry_telegram-0.6.0.dist-info/RECORD
